arvio_emaxx_reader/__init__.py
arvio_emaxx_reader/arvio_emaxx_reader.py
arvio_emaxx_reader-0.2.0.dist-info/LICENSE
arvio_emaxx_reader-0.2.0.dist-info/METADATA
arvio_emaxx_reader-0.2.0.dist-info/WHEEL
arvio_emaxx_reader-0.2.0.dist-info/top_level.txt
arvio_emaxx_reader-0.2.0.dist-info/RECORD
