Metadata-Version: 2.1
Name: arvio-emaxx-reader
Version: 0.2.0
Summary: A library to read from an Arvio Emaxx on the local network
Home-page: https://github.com/jamiepenney/arvio_emaxx_reader
Author: Jamie Penney
License: UNKNOWN
Platform: UNKNOWN
Classifier: Programming Language :: Python :: 3
Classifier: License :: OSI Approved :: Apache Software License
Classifier: Operating System :: OS Independent
Requires-Dist: requests-async (>=0.6.0)
